prtg/__init__.py
prtg/__main__.py
prtg/version.py
prtg-0.1.0.dev0.dist-info/LICENSE
prtg-0.1.0.dev0.dist-info/METADATA
prtg-0.1.0.dev0.dist-info/WHEEL
prtg-0.1.0.dev0.dist-info/top_level.txt
prtg-0.1.0.dev0.dist-info/RECORD
